<?xml version="1.0" encoding="utf-16"?>
<AutoReplacement xmlns:xsi="http://www.w3.org/2001/XMLSchema-instance" xmlns:xsd="http://www.w3.org/2001/XMLSchema">
  <Token>comp</Token>
  <Name />
  <CaseSensitive>false</CaseSensitive>
  <SelectReplacement>false</SelectReplacement>
  <Replacement>;WITH LIST_COMPUTED_COLUMNS
 AS
(
SELECT IIF(SO.type = 'TT', SCHEMA_NAME(STT.schema_id), SCHEMA_NAME(SO.schema_id)) AS Sch_Name,
       IIF(SO.type = 'TT', STT.name, SO.name) AS ObjectName,
	  SO.Type_Desc AS Object_Type,
       CC.name AS Column_Name,
	  CC.Definition,
       ST.name AS Datatype,
	  CC.Max_Length,
       CC.Precision,
       CC.Scale,
       IIF(CC.is_nullable = 1, 'YES', 'NO') AS Is_Nullable,
	  IIF(CC.is_persisted = 1, 'YES', 'NO') AS Is_Persisted
  FROM sys.computed_columns AS CC
       LEFT JOIN sys.types AS ST ON CC.system_type_id = ST.system_type_id
	        AND CC.user_type_id = ST.user_type_id	   
	  LEFT JOIN sys.objects AS SO ON CC.object_id = SO.object_id
	  LEFT JOIN sys.table_types AS STT ON CC.object_id = STT.type_table_object_id
)
SELECT *
  FROM LIST_COMPUTED_COLUMNS
 WHERE 1 = 1
   --AND Sch_Name = ''
   --AND Object_Type = ''
   --AND ObjectName = ''
   --AND Column_Name = ''
 ORDER BY 1, 3, 2
;</Replacement>
  <CursorPositionMarker>#</CursorPositionMarker>
</AutoReplacement>